LICENSE
MANIFEST.in
README.rst
setup.py
ws_recorder.egg-info/PKG-INFO
ws_recorder.egg-info/SOURCES.txt
ws_recorder.egg-info/dependency_links.txt
ws_recorder.egg-info/requires.txt
ws_recorder.egg-info/top_level.txt
wsrecorder/__init__.py
wsrecorder/tools.py
wsrecorder/wsrecorder.py