Metadata-Version: 1.1
Name: ws-recorder
Version: 0.9.0
Summary: Tool to record Web Service calls and to serve them afterwards
Home-page: http://ws-recorder.kjw.pt
Author: Kamil Kujawinski
Author-email: kamil@kujawinski.net
License: LGPL
Platform: UNKNOWN
Classifier: Environment :: Console
Classifier: Environment :: Web Environment
Classifier: Intended Audience :: Developers
Classifier: License :: OSI Approved :: GNU Lesser General Public License v3 or later (LGPLv3+)
Classifier: Operating System :: OS Independent
Classifier: Programming Language :: Python
Classifier: Programming Language :: Python :: 2.6
Classifier: Programming Language :: Python :: 2.7
Classifier: Topic :: Internet
Classifier: Topic :: Software Development :: Testing
Classifier: Topic :: Internet :: WWW/HTTP :: Dynamic Content
